fastwarc/__init__.py
fastwarc/stream_io.cpython-312-darwin.so
fastwarc/warc.cpython-312-darwin.so
fastwarc/cli.py
fastwarc/warc.pyi
fastwarc/py.typed
fastwarc/tools.cpython-312-darwin.so
fastwarc/tools.pyi
fastwarc/stream_io.pyi
fastwarc/.dylibs/liblz4.1.10.0.dylib
fastwarc/.dylibs/libz.1.3.1.dylib
fastwarc-0.15.2.dist-info/RECORD
fastwarc-0.15.2.dist-info/WHEEL
fastwarc-0.15.2.dist-info/entry_points.txt
fastwarc-0.15.2.dist-info/top_level.txt
fastwarc-0.15.2.dist-info/METADATA
