Metadata-Version: 2.4
Name: FastWARC
Version: 0.15.2
Summary: A high-performance WARC parsing library for Python written in C++/Cython.
Author: Janek Bevendorff
License: Apache License 2.0
Project-URL: repository, https://github.com/chatnoir-eu/chatnoir-resiliparse
Project-URL: homepage, https://resiliparse.chatnoir.eu
Project-URL: documentation, https://resiliparse.chatnoir.eu
Requires-Python: >=3.8
Requires-Dist: brotli
Requires-Dist: click
Requires-Dist: tqdm
Provides-Extra: all
Provides-Extra: test
Requires-Dist: pytest>=7.2.2; extra == "test"
Requires-Dist: pytest-cov>=4.0.0; extra == "test"
Requires-Dist: lz4; extra == "test"
